{"localpaths":{"ontonotes":"../../data/ontonotes/","ewt":"../../data/google/ewt/","questionbank":"../../data/google/questionbank/", "boltdf":"../../data/bolt/df/df/00/", "boltdf2":"../../data/bolt/df2/"},
"modifications":{"ontonotes":["",""], "ewt":["/00","/penntree"], "questionbank":["questionbank/00",""],"boltdf":["bolt/df/df/00",""],"boltdf2":["00",""]},             
"filemoddict":{"questionbank":[["QB-revised","QB-revised.v1"]]},
"metadata":{"ontonotes":"data/files/data/english/annotations/", "ewt":"data/", "questionbank":"data/","boltdf":"/data/penntree/","boltdf2":"/data/" 
},
"filemoddict":{"questionbank":[["QB-revised","QB-revised.v1"]]},
"flagdict":{"questionbank":["--topless"],"ewt":["--topless"], "ontonotes":[],"boltdf":["--topless"],"boltdf2":["--topless"]}}	  
